README.md
setup.py
nem_python/__init__.py
nem_python/dict_math.py
nem_python/ed25519.py
nem_python/nem_connect.py
nem_python/python_sha3.py
nem_python/transaction_builder.py
nem_python/transaction_reform.py
nem_python/utils.py
nem_python.egg-info/PKG-INFO
nem_python.egg-info/SOURCES.txt
nem_python.egg-info/dependency_links.txt
nem_python.egg-info/requires.txt
nem_python.egg-info/top_level.txt
test/test_account_que.py
test/test_by_console.py
test/test_encryption.py
test/test_mosaic_calc.py
test/test_sending.py