Metadata-Version: 1.1
Name: nem-python
Version: 0.1.0
Summary: Package Dependency: Validates package requirements
Home-page: https://github.com/namuyan/nem-python
Author: namuyan
Author-email: UNKNOWN
License: MIT
Platform: UNKNOWN
Classifier: Programming Language :: Python :: 3
Classifier: Programming Language :: Python :: 3.5
Classifier: Programming Language :: Python :: 3.6
